README.md
setup.py
spyros/__init__.py
spyrosavr.egg-info/PKG-INFO
spyrosavr.egg-info/SOURCES.txt
spyrosavr.egg-info/dependency_links.txt
spyrosavr.egg-info/top_level.txt