Metadata-Version: 1.0
Name: spyrosavr
Version: 0.1
Summary: hello
Home-page: https://github-isl-01.ca.com/avrsp01/pythonpackaging/spyros
Author: Spyros
Author-email: avrsp01@ca.com
License: UNKNOWN
Platform: UNKNOWN
